FileEase/__init__.py
FileEase/images.py
FileEase/main.py
fileease-0.0.4.dist-info/LICENSE
fileease-0.0.4.dist-info/METADATA
fileease-0.0.4.dist-info/WHEEL
fileease-0.0.4.dist-info/top_level.txt
fileease-0.0.4.dist-info/RECORD
