Metadata-Version: 2.1
Name: fileease
Version: 0.0.4
Summary: A simple file management tool
Author-email: METECH <metech.mc@gmail.com>
License: MIT
Project-URL: homepage, https://github.com/ME-TECH-ELECTRONICS/FileEase
Project-URL: repository, https://github.com/ME-TECH-ELECTRONICS/FileEase
Requires-Python: >=3.10
License-File: LICENSE
Requires-Dist: pypdf>=5.1.0
Requires-Dist: pikepdf>=9.4.2
Requires-Dist: pillow>=11.0.0
